wordlebot/__init__.py
wordlebot/guessing.py
wordlebot-0.2.dist-info/LICENSE
wordlebot-0.2.dist-info/METADATA
wordlebot-0.2.dist-info/WHEEL
wordlebot-0.2.dist-info/entry_points.txt
wordlebot-0.2.dist-info/top_level.txt
wordlebot-0.2.dist-info/RECORD
